{
  "annotations": [
    {
      "class": "obj",
      "height": 186.85833798980818,
      "id": "binder_0",
      "type": "rect",
      "width": 164.60729029932025,
      "x": 475.75112215690905,
      "y": 218
    },
    {
      "class": "obj",
      "height": 37.14341456557423,
      "id": "marker_0",
      "type": "rect",
      "width": 66.1847594121851,
      "x": 240,
      "y": 328
    },
    {
      "class": "obj",
      "height": 45.812426694281896,
      "id": "pliers_0",
      "type": "rect",
      "width": 52.02718639800173,
      "x": 361,
      "y": 349
    },
    {
      "class": "obj",
      "height": 61.927682026300914,
      "id": "shampoo_1",
      "type": "rect",
      "width": 24.895802094763013,
      "x": 454.59181699204163,
      "y": 167
    },
    {
      "class": "obj",
      "height": 44.10549504307005,
      "id": "keyboard_1",
      "type": "rect",
      "width": 63.40034403497671,
      "x": 443.76737523676485,
      "y": 155.63625508523538
    },
    {
      "class": "obj",
      "height": 21.89349387328511,
      "id": "plate_1",
      "type": "rect",
      "width": 54.130425096143966,
      "x": 404.06527058567497,
      "y": 183.76327320318333
    },
    {
      "class": "obj",
      "height": 23.57923838537468,
      "id": "apple_2",
      "type": "rect",
      "width": 17.2466514942367,
      "x": 366.0501552746473,
      "y": 164.29304990529405
    },
    {
      "class": "obj",
      "height": 14.729024071434651,
      "id": "scissors_0",
      "type": "rect",
      "width": 38.41201474983529,
      "x": 383.9469071872667,
      "y": 165.28981960955002
    },
    {
      "class": "obj",
      "height": 130.22921725131545,
      "id": "cereal_box_0",
      "type": "rect",
      "width": 55.39929728220149,
      "x": 311.9935992670708,
      "y": 120.1993599267071
    },
    {
      "class": "obj",
      "height": 23.340575197457554,
      "id": "comb_2",
      "type": "rect",
      "width": 41.279230921324796,
      "x": 410,
      "y": 255
    },
    {
      "class": "obj",
      "height": 22.11110227768046,
      "id": "pliers_2",
      "type": "rect",
      "width": 55.61036660060458,
      "x": 376.2025602931717,
      "y": 226
    },
    {
      "class": "obj",
      "height": 29.422980941649314,
      "id": "orange_1",
      "type": "rect",
      "width": 28.001706498633126,
      "x": 475.0121777729417,
      "y": 221.47345359363337
    },
    {
      "class": "obj",
      "height": 37.299733648742745,
      "id": "orange_0",
      "type": "rect",
      "width": 34.67023207683863,
      "x": 384.6662152164885,
      "y": 286
    },
    {
      "class": "obj",
      "height": 15.346829848978985,
      "id": "rubber_eraser_2",
      "type": "rect",
      "width": 17.360982814217834,
      "x": 314,
      "y": 279
    },
    {
      "class": "obj",
      "height": 16.897883680411866,
      "id": "cell_phone_0",
      "type": "rect",
      "width": 24.0844537306117,
      "x": 362.15165988635283,
      "y": 198.55529020835306
    },
    {
      "class": "obj",
      "height": 46.97891987895707,
      "id": "ball_1",
      "type": "rect",
      "width": 46.99415032003129,
      "x": 176,
      "y": 325.33243043297693
    }
  ],
  "class": "image",
  "filename": "wp_2_3_6_011.png"
}
