{
  "annotations": [
    {
      "class": "obj",
      "height": 104.18769270445,
      "id": "hand_towel_0",
      "type": "rect",
      "width": 107.07277764365358,
      "x": 533.6140350877192,
      "y": 374.8070175438596
    },
    {
      "class": "obj",
      "height": 69.42232211064004,
      "id": "toothbrush_0",
      "type": "rect",
      "width": 24.275984009471543,
      "x": 505,
      "y": 338
    },
    {
      "class": "obj",
      "height": 38.350477981396125,
      "id": "camera_1",
      "type": "rect",
      "width": 60.944569291143324,
      "x": 556,
      "y": 317
    },
    {
      "class": "obj",
      "height": 102.59228892367446,
      "id": "cap_0",
      "type": "rect",
      "width": 122.70253925137285,
      "x": 370,
      "y": 308
    },
    {
      "class": "obj",
      "height": 58.561942493261256,
      "id": "bowl_0",
      "type": "rect",
      "width": 80.96051082630474,
      "x": 435,
      "y": 257
    },
    {
      "class": "obj",
      "height": 86.27473950181215,
      "id": "kleenex_0",
      "type": "rect",
      "width": 94.77155644922743,
      "x": 504.9263253679294,
      "y": 223.27942496655191
    },
    {
      "class": "obj",
      "height": 32.48101832805682,
      "id": "notebook_0",
      "type": "rect",
      "width": 95.1169629072001,
      "x": 544.4267742306931,
      "y": 180
    },
    {
      "class": "obj",
      "height": 100.90556686907553,
      "id": "cereal_box_0",
      "type": "rect",
      "width": 39.246834332460054,
      "x": 508.67654979931103,
      "y": 147.72057503344814
    },
    {
      "class": "obj",
      "height": 46.02566208422107,
      "id": "notebook_2",
      "type": "rect",
      "width": 71.90897341968187,
      "x": 567.8679242975892,
      "y": 255
    },
    {
      "class": "obj",
      "height": 48.51135296147109,
      "id": "keyboard_2",
      "type": "rect",
      "width": 74.06437425636383,
      "x": 548.0736746320706,
      "y": 209.8823001337925
    }
  ],
  "class": "image",
  "filename": "wp_3_3_3_017.png"
}
