{
  "annotations": [
    {
      "class": "obj",
      "height": 215.05882352941174,
      "id": "cereal_box_0",
      "type": "rect",
      "width": 128.47058823529414,
      "x": 279,
      "y": 183
    },
    {
      "class": "obj",
      "height": 79.05882352941177,
      "id": "coffee_mug_0",
      "type": "rect",
      "width": 58.82352941176471,
      "x": 139,
      "y": 343
    },
    {
      "class": "obj",
      "height": 64.41385064664166,
      "id": "coffee_mug_1",
      "type": "rect",
      "width": 51.063829787234056,
      "x": 195,
      "y": 287
    },
    {
      "class": "obj",
      "height": 38.38130997079685,
      "id": "ball_1",
      "type": "rect",
      "width": 38.04755944931165,
      "x": 217,
      "y": 268
    },
    {
      "class": "obj",
      "height": 21.026282853566954,
      "id": "rubber_eraser_2",
      "type": "rect",
      "width": 27.033792240300386,
      "x": 163,
      "y": 303
    },
    {
      "class": "obj",
      "height": 27.033792240300386,
      "id": "marker_0",
      "type": "rect",
      "width": 48.393825615352554,
      "x": 145,
      "y": 270
    },
    {
      "class": "obj",
      "height": 60.34959743059272,
      "id": "scissors_0",
      "type": "rect",
      "width": 86.61284816427664,
      "x": 25,
      "y": 322
    },
    {
      "class": "obj",
      "height": 13.933551271702015,
      "id": "comb_2",
      "type": "rect",
      "width": 32.903325894621645,
      "x": 253,
      "y": 259
    },
    {
      "class": "obj",
      "height": 29.351109690896124,
      "id": "cell_phone_0",
      "type": "rect",
      "width": 45.44687952138759,
      "x": 141,
      "y": 238
    },
    {
      "class": "obj",
      "height": 58.702219381792304,
      "id": "keyboard_1",
      "type": "rect",
      "width": 108.88314885332443,
      "x": 177,
      "y": 197
    },
    {
      "class": "obj",
      "height": 21.35672532485853,
      "id": "apple_2",
      "type": "rect",
      "width": 20.855393744462788,
      "x": 232,
      "y": 167
    },
    {
      "class": "obj",
      "height": 17.145540049534304,
      "id": "pliers_2",
      "type": "rect",
      "width": 42.512918017558775,
      "x": 219,
      "y": 187
    },
    {
      "class": "obj",
      "height": 27.507265251217603,
      "id": "stapler_2",
      "type": "rect",
      "width": 40.47787788634423,
      "x": 159.00135435053448,
      "y": 183.667569567023
    },
    {
      "class": "obj",
      "height": 23.662850594678957,
      "id": "marker_2",
      "type": "rect",
      "width": 32.285753777485695,
      "x": 150,
      "y": 174
    },
    {
      "class": "obj",
      "height": 65.56659180950192,
      "id": "food_box_1",
      "type": "rect",
      "width": 98.46823896300651,
      "x": 40,
      "y": 195
    },
    {
      "class": "obj",
      "height": 102.01877642561492,
      "id": "binder_0",
      "type": "rect",
      "width": 72.43096423721153,
      "x": 60,
      "y": 98
    },
    {
      "class": "obj",
      "height": 49.73393274321313,
      "id": "shampoo_1",
      "type": "rect",
      "width": 20.027087010689854,
      "x": 212.45401470506812,
      "y": 130.67674274475124
    },
    {
      "class": "obj",
      "height": 18.691947876643866,
      "id": "tomato_1",
      "type": "rect",
      "width": 18.858840268399604,
      "x": 188.0877255087288,
      "y": 163.22075913712223
    }
  ],
  "class": "image",
  "filename": "wp_1_3_44_002.png"
}
