{
  "annotations": [
    {
      "class": "obj",
      "height": 87.85214065372674,
      "id": "notebook_0",
      "type": "rect",
      "width": 124.16167845598159,
      "x": 373,
      "y": 296
    },
    {
      "class": "obj",
      "height": 98.8944054705726,
      "id": "cereal_box_0",
      "type": "rect",
      "width": 66.1770128205189,
      "x": 331.3598221731498,
      "y": 153.6127838539978
    },
    {
      "class": "obj",
      "height": 46.3028485638674,
      "id": "keyboard_2",
      "type": "rect",
      "width": 129.23656014174037,
      "x": 273.99086867571583,
      "y": 233.99999999999997
    },
    {
      "class": "obj",
      "height": 42.347338849827,
      "id": "camera_0",
      "type": "rect",
      "width": 60.795696967452656,
      "x": 289,
      "y": 344
    },
    {
      "class": "obj",
      "height": 40.61249789122394,
      "id": "flashlight_1",
      "type": "rect",
      "width": 29.13301485198423,
      "x": 408,
      "y": 263
    },
    {
      "class": "obj",
      "height": 59.3798017752992,
      "id": "toothpaste_0",
      "type": "rect",
      "width": 22.892050136872136,
      "x": 302,
      "y": 178
    },
    {
      "class": "obj",
      "height": 53.31565744297228,
      "id": "kleenex_0",
      "type": "rect",
      "width": 76.79720707818777,
      "x": 241.17991108657486,
      "y": 174.39634747028634
    },
    {
      "class": "obj",
      "height": 69.83247346356671,
      "id": "greens_1",
      "type": "rect",
      "width": 213.1706538145403,
      "x": 137,
      "y": 253
    },
    {
      "class": "obj",
      "height": 47.569261695390594,
      "id": "flashlight_0",
      "type": "rect",
      "width": 67.5789152631005,
      "x": 200,
      "y": 330
    },
    {
      "class": "obj",
      "height": 26.157250650019876,
      "id": "rubber_eraser_1",
      "type": "rect",
      "width": 30.419978772907328,
      "x": 211,
      "y": 408
    },
    {
      "class": "obj",
      "height": 36.689367692507545,
      "id": "cap_0",
      "type": "rect",
      "width": 65.4428909353098,
      "x": 238.98173735143166,
      "y": 153.81095758914103
    },
    {
      "class": "obj",
      "height": 55.02609517205744,
      "id": "notebook_2",
      "type": "rect",
      "width": 126.83880696143285,
      "x": 176,
      "y": 216
    },
    {
      "class": "obj",
      "height": 22.698322603571057,
      "id": "marker_1",
      "type": "rect",
      "width": 46.03314634758192,
      "x": 182,
      "y": 219
    },
    {
      "class": "obj",
      "height": 14.034914614754655,
      "id": "toothbrush_0",
      "type": "rect",
      "width": 34.94105745853018,
      "x": 221.93064993179482,
      "y": 181.48766071312784
    },
    {
      "class": "obj",
      "height": 29.458980767213347,
      "id": "hand_towel_0",
      "type": "rect",
      "width": 74.31828213189871,
      "x": 148.55799590829284,
      "y": 171.17991108657486
    },
    {
      "class": "obj",
      "height": 19.151172447240043,
      "id": "camera_1",
      "type": "rect",
      "width": 33.83711116008392,
      "x": 213.57625855686118,
      "y": 193.40547879457048
    },
    {
      "class": "obj",
      "height": 13.924987881850399,
      "id": "scissors_2",
      "type": "rect",
      "width": 68.39537272092993,
      "x": 132.15251711372238,
      "y": 220.97260602714755
    },
    {
      "class": "obj",
      "height": 25.31203577251972,
      "id": "calculator_1",
      "type": "rect",
      "width": 62.40769373488183,
      "x": 117.7561696434361,
      "y": 231.9817373514317
    },
    {
      "class": "obj",
      "height": 25.55435076136584,
      "id": "notebook_1",
      "type": "rect",
      "width": 105.36820598289333,
      "x": 101.54886458400878,
      "y": 197.7926949405727
    }
  ],
  "class": "image",
  "filename": "wp_3_2_2_011.png"
}
