{
  "annotations": [
    {
      "class": "obj",
      "height": 81.90631116879666,
      "id": "hand_towel_2",
      "type": "rect",
      "width": 139.9522685662293,
      "x": 226.39634747028634,
      "y": 256.9908686757159
    },
    {
      "class": "obj",
      "height": 44.73234558265045,
      "id": "keyboard_0",
      "type": "rect",
      "width": 138.75386746139654,
      "x": 186.5444740969005,
      "y": 222.20575033448125
    },
    {
      "class": "obj",
      "height": 50.771717481524774,
      "id": "pear_2",
      "type": "rect",
      "width": 40.68232944831158,
      "x": 214,
      "y": 319
    },
    {
      "class": "obj",
      "height": 38.92520298879913,
      "id": "cereal_box_2",
      "type": "rect",
      "width": 20.885766156061845,
      "x": 177,
      "y": 290
    },
    {
      "class": "obj",
      "height": 16.4722790662924,
      "id": "camera_2",
      "type": "rect",
      "width": 34.82710431158962,
      "x": 167.72235816339168,
      "y": 211
    },
    {
      "class": "obj",
      "height": 23.68390077925943,
      "id": "pliers_1",
      "type": "rect",
      "width": 67.82153816430466,
      "x": 134.56712723257706,
      "y": 258.60365252971366
    },
    {
      "class": "obj",
      "height": 57.90301655518877,
      "id": "cereal_box_2",
      "type": "rect",
      "width": 49.167741850445644,
      "x": 149.32635292837494,
      "y": 126.64490980477498
    },
    {
      "class": "obj",
      "height": 43.111228417207826,
      "id": "calculator_2",
      "type": "rect",
      "width": 88.2102151568856,
      "x": 109.78356361628855,
      "y": 368
    },
    {
      "class": "obj",
      "height": 16.83090411339282,
      "id": "calculator_0",
      "type": "rect",
      "width": 25.490075304788657,
      "x": 157.0243555458833,
      "y": 192.355090195225
    },
    {
      "class": "obj",
      "height": 24.007609040906743,
      "id": "lightbulb_2",
      "type": "rect",
      "width": 27.673059124460114,
      "x": 135.27326011564165,
      "y": 236.88434081497954
    },
    {
      "class": "obj",
      "height": 35.40286032909506,
      "id": "onion_2",
      "type": "rect",
      "width": 45.42579495850278,
      "x": 87.73790699486781,
      "y": 333.3780848217181
    },
    {
      "class": "obj",
      "height": 23.168715625537033,
      "id": "ball_2",
      "type": "rect",
      "width": 23.808775594023547,
      "x": 112.49780913951663,
      "y": 209.31417515543328
    },
    {
      "class": "obj",
      "height": 19.907324713247306,
      "id": "garlic_1",
      "type": "rect",
      "width": 23.41682695900969,
      "x": 63.74671370927494,
      "y": 245.17145621114165
    },
    {
      "class": "obj",
      "height": 42.21298732284674,
      "id": "bell_pepper_0",
      "type": "rect",
      "width": 43.402029733705795,
      "x": 63.945212054295126,
      "y": 293.17991108657486
    },
    {
      "class": "obj",
      "height": 13.35213109120653,
      "id": "flashlight_2",
      "type": "rect",
      "width": 40.61858826693357,
      "x": 50.207989529966625,
      "y": 234.88163660159165
    },
    {
      "class": "obj",
      "height": 23.183106825393253,
      "id": "potato_1",
      "type": "rect",
      "width": 22.842765331280894,
      "x": 52.456894099724934,
      "y": 206.00000000000003
    },
    {
      "class": "obj",
      "height": 19.25517852100313,
      "id": "stapler_0",
      "type": "rect",
      "width": 42.44572199520394,
      "x": 33.036533318824944,
      "y": 189.8285437888583
    },
    {
      "class": "obj",
      "height": 17.990239786046686,
      "id": "lemon_0",
      "type": "rect",
      "width": 19.3957272693316,
      "x": 100.7369828773829,
      "y": 182.77983269709165
    }
  ],
  "class": "image",
  "filename": "wp_9_2_50_008.png"
}
