{
  "annotations": [
    {
      "class": "obj",
      "height": 26.741845317790137,
      "id": "mushroom_0",
      "type": "rect",
      "width": 42.376668179451656,
      "x": 380,
      "y": 273
    },
    {
      "class": "obj",
      "height": 47.75039905435614,
      "id": "bell_pepper_2",
      "type": "rect",
      "width": 41.05452831477541,
      "x": 314,
      "y": 283.99086867571583
    },
    {
      "class": "obj",
      "height": 79.9433466843029,
      "id": "greens_2",
      "type": "rect",
      "width": 97.83870782724443,
      "x": 274,
      "y": 185.39712483275937
    },
    {
      "class": "obj",
      "height": 49.6620295391983,
      "id": "cap_1",
      "type": "rect",
      "width": 64.69634818131468,
      "x": 241.6765497993112,
      "y": 190
    },
    {
      "class": "obj",
      "height": 28.35688623415973,
      "id": "cell_phone_1",
      "type": "rect",
      "width": 27.243475067936316,
      "x": 262,
      "y": 271
    },
    {
      "class": "obj",
      "height": 145.9780620589667,
      "id": "pitcher_0",
      "type": "rect",
      "width": 62.441845240840124,
      "x": 206.9634747028634,
      "y": 216.0091313242841
    },
    {
      "class": "obj",
      "height": 44.1654225467384,
      "id": "shampoo_0",
      "type": "rect",
      "width": 19.47516527194613,
      "x": 227.42677423069304,
      "y": 122.88230013379254
    },
    {
      "class": "obj",
      "height": 28.34961247298955,
      "id": "food_box_0",
      "type": "rect",
      "width": 44.93867594209181,
      "x": 210.79424966551872,
      "y": 162.8823001337925
    },
    {
      "class": "obj",
      "height": 56.22883278814089,
      "id": "food_bag_0",
      "type": "rect",
      "width": 27.150989329733378,
      "x": 187.8238990634524,
      "y": 145.60287516724065
    },
    {
      "class": "obj",
      "height": 22.16593862439072,
      "id": "cell_phone_2",
      "type": "rect",
      "width": 44.15890380339885,
      "x": 165,
      "y": 230
    },
    {
      "class": "obj",
      "height": 18.93425416804712,
      "id": "dry_battery_2",
      "type": "rect",
      "width": 18.995378176074958,
      "x": 167,
      "y": 348
    },
    {
      "class": "obj",
      "height": 34.57569964326615,
      "id": "food_cup_1",
      "type": "rect",
      "width": 26.94478362997522,
      "x": 172.10332403000427,
      "y": 182.44115006689628
    },
    {
      "class": "obj",
      "height": 42.298800484342024,
      "id": "water_bottle_2",
      "type": "rect",
      "width": 22.404708643409183,
      "x": 159.42102604403073,
      "y": 138.9022708319824
    },
    {
      "class": "obj",
      "height": 14.71003219208805,
      "id": "lightbulb_1",
      "type": "rect",
      "width": 26.468136218149482,
      "x": 137.5195325745213,
      "y": 187.4611207650862
    },
    {
      "class": "obj",
      "height": 21.378069907211,
      "id": "pear_1",
      "type": "rect",
      "width": 44.05326513957548,
      "x": 139.662173963108,
      "y": 214.72057503344814
    },
    {
      "class": "obj",
      "height": 45.786525201919005,
      "id": "toothbrush_2",
      "type": "rect",
      "width": 76.51737736728131,
      "x": 114.3689534974339,
      "y": 300.17991108657486
    },
    {
      "class": "obj",
      "height": 14.164270280370005,
      "id": "toothpaste_1",
      "type": "rect",
      "width": 26.78150578972249,
      "x": 114.07538907642996,
      "y": 174.16510568007115
    },
    {
      "class": "obj",
      "height": 11.849359814658186,
      "id": "glue_stick_0",
      "type": "rect",
      "width": 35.881864227486005,
      "x": 108.50338587633622,
      "y": 247.33378478351148
    },
    {
      "class": "obj",
      "height": 41.24145966778684,
      "id": "instant_noodles_2",
      "type": "rect",
      "width": 85.64391614731991,
      "x": 103.58792290114584,
      "y": 256.1043297049809
    },
    {
      "class": "obj",
      "height": 48.351679448696586,
      "id": "kleenex_1",
      "type": "rect",
      "width": 61.44255396857402,
      "x": 76.9269494057268,
      "y": 183
    }
  ],
  "class": "image",
  "filename": "wp_5_2_50_008.png"
}
