{
  "annotations": [
    {
      "class": "obj",
      "height": 69.48538511485702,
      "id": "keyboard_2",
      "type": "rect",
      "width": 185.4716213921613,
      "x": 454.4561403508772,
      "y": 347.8070175438597
    },
    {
      "class": "obj",
      "height": 59.048357568152426,
      "id": "marker_1",
      "type": "rect",
      "width": 68.89849500554945,
      "x": 448,
      "y": 416
    },
    {
      "class": "obj",
      "height": 42.06543779914034,
      "id": "calculator_1",
      "type": "rect",
      "width": 94.13537705303443,
      "x": 336,
      "y": 356
    },
    {
      "class": "obj",
      "height": 17.648870428170426,
      "id": "rubber_eraser_1",
      "type": "rect",
      "width": 28.238192685072676,
      "x": 337,
      "y": 326
    },
    {
      "class": "obj",
      "height": 46.20520411532078,
      "id": "toothpaste_0",
      "type": "rect",
      "width": 85.7231088147974,
      "x": 507.9356725146199,
      "y": 309
    },
    {
      "class": "obj",
      "height": 90.83081161272935,
      "id": "notebook_2",
      "type": "rect",
      "width": 163.876907592091,
      "x": 208,
      "y": 271
    },
    {
      "class": "obj",
      "height": 81.35690418967283,
      "id": "notebook_1",
      "type": "rect",
      "width": 118.3953139895583,
      "x": 364,
      "y": 273
    },
    {
      "class": "obj",
      "height": 87.75829899141883,
      "id": "hand_towel_0",
      "type": "rect",
      "width": 193.66419977717916,
      "x": 255,
      "y": 391
    },
    {
      "class": "obj",
      "height": 54.46008739282473,
      "id": "flashlight_0",
      "type": "rect",
      "width": 64.69702288304387,
      "x": 271,
      "y": 334
    },
    {
      "class": "obj",
      "height": 123.56164958320005,
      "id": "notebook_0",
      "type": "rect",
      "width": 155.54841469907822,
      "x": 95,
      "y": 351
    },
    {
      "class": "obj",
      "height": 62.305970958030116,
      "id": "bowl_0",
      "type": "rect",
      "width": 84.17768534191515,
      "x": 119.80701754385964,
      "y": 277
    },
    {
      "class": "obj",
      "height": 50.994152046783654,
      "id": "cereal_box_0",
      "type": "rect",
      "width": 112.28070175438596,
      "x": 41,
      "y": 226
    },
    {
      "class": "obj",
      "height": 43.9766081871345,
      "id": "camera_0",
      "type": "rect",
      "width": 58.47953216374268,
      "x": 41.74269005847954,
      "y": 371
    },
    {
      "class": "obj",
      "height": 89.35672514619881,
      "id": "greens_1",
      "type": "rect",
      "width": 125.84795321637426,
      "x": 0.4678362573099415,
      "y": 301.2865497076023
    },
    {
      "class": "obj",
      "height": 71.57894736842107,
      "id": "kleenex_0",
      "type": "rect",
      "width": 87.953216374269,
      "x": 0,
      "y": 246.0818713450292
    }
  ],
  "class": "image",
  "filename": "wp_3_1_51_011.png"
}
