{
  "annotations": [
    {
      "class": "obj",
      "height": 61.11577093198861,
      "id": "cell_phone_1",
      "type": "rect",
      "width": 81.48985452088013,
      "x": 226.68661606735515,
      "y": 411.35481730330554
    },
    {
      "class": "obj",
      "height": 51.070758526130305,
      "id": "cell_phone_2",
      "type": "rect",
      "width": 103.72242105751097,
      "x": 67.66820123595039,
      "y": 418.0092074157024
    },
    {
      "class": "obj",
      "height": 69.23976608187138,
      "id": "bell_pepper_2",
      "type": "rect",
      "width": 69.23976608187132,
      "x": 438.8304093567251,
      "y": 408.4210526315789
    },
    {
      "class": "obj",
      "height": 44.520779920709515,
      "id": "toothpaste_2",
      "type": "rect",
      "width": 75.25193774208424,
      "x": 380.98755914447895,
      "y": 340.0126820493127
    },
    {
      "class": "obj",
      "height": 30.45732135415392,
      "id": "shampoo_2",
      "type": "rect",
      "width": 79.35669050073122,
      "x": 249.24707016426854,
      "y": 296.46988951153463
    },
    {
      "class": "obj",
      "height": 55.884993310374085,
      "id": "instant_noodles_1",
      "type": "rect",
      "width": 41.354895049676884,
      "x": 361.2964817515686,
      "y": 240.58489620116055
    },
    {
      "class": "obj",
      "height": 40.58088789232818,
      "id": "food_box_0",
      "type": "rect",
      "width": 146.56398345578714,
      "x": 69.73608890235033,
      "y": 285.24818285481155
    },
    {
      "class": "obj",
      "height": 48.94620065412602,
      "id": "food_cup_0",
      "type": "rect",
      "width": 51.77001992263324,
      "x": 99.53962921488117,
      "y": 312.5026657148042
    },
    {
      "class": "obj",
      "height": 81.42012224195952,
      "id": "water_bottle_2",
      "type": "rect",
      "width": 40.23942457622857,
      "x": 174.37083983032375,
      "y": 274.3811055899561
    },
    {
      "class": "obj",
      "height": 34.827104311589665,
      "id": "peach_2",
      "type": "rect",
      "width": 34.12114949446283,
      "x": 280.73469894409754,
      "y": 326.6217620573406
    },
    {
      "class": "obj",
      "height": 56.94702191489654,
      "id": "mushroom_0",
      "type": "rect",
      "width": 52.475974739760034,
      "x": 325.2098524230871,
      "y": 384.74537533411535
    },
    {
      "class": "obj",
      "height": 37.42690058479536,
      "id": "shampoo_0",
      "type": "rect",
      "width": 84.21052631578952,
      "x": 0,
      "y": 321.87134502923993
    },
    {
      "class": "obj",
      "height": 16.52234678381916,
      "id": "dry_battery_2",
      "type": "rect",
      "width": 29.70684573252329,
      "x": 123.16658511574259,
      "y": 373.0044955740985
    }
  ],
  "class": "image",
  "filename": "wp_6_1_90_002.png"
}
