{
  "annotations": [
    {
      "class": "obj",
      "height": 19.817373514317012,
      "id": "rubber_eraser_1",
      "type": "rect",
      "width": 27.34797544975754,
      "x": 463.7265402350193,
      "y": 353.1455960251301
    },
    {
      "class": "obj",
      "height": 33.41519467733599,
      "id": "camera_0",
      "type": "rect",
      "width": 47.53429101987234,
      "x": 378.39178197997387,
      "y": 296.97165973801435
    },
    {
      "class": "obj",
      "height": 116.24722655354924,
      "id": "cereal_box_0",
      "type": "rect",
      "width": 95.0685820397447,
      "x": 103.77535811764211,
      "y": 168.48788302093368
    },
    {
      "class": "obj",
      "height": 72.24270961931092,
      "id": "keyboard_2",
      "type": "rect",
      "width": 148.72114814138283,
      "x": 111.7761793784127,
      "y": 250.6139600800201
    },
    {
      "class": "obj",
      "height": 153.6228277549667,
      "id": "greens_1",
      "type": "rect",
      "width": 141.34627348513135,
      "x": 176.848741238439,
      "y": 268.09340135208015
    },
    {
      "class": "obj",
      "height": 53.50690848865611,
      "id": "notebook_0",
      "type": "rect",
      "width": 127.42571169705883,
      "x": 301.0259036824764,
      "y": 242.7628255503842
    },
    {
      "class": "obj",
      "height": 76.03991614776061,
      "id": "comb_1",
      "type": "rect",
      "width": 104.4071387521065,
      "x": 62.64428325126391,
      "y": 364.83400182811556
    },
    {
      "class": "obj",
      "height": 107.7718065443442,
      "id": "notebook_2",
      "type": "rect",
      "width": 148.88063996847555,
      "x": 1.1110495520035488,
      "y": 296.0947056089458
    },
    {
      "class": "obj",
      "height": 76.12224378076175,
      "id": "toothpaste_0",
      "type": "rect",
      "width": 31.665760123638847,
      "x": 78.82322830487936,
      "y": 218.9871842727388
    },
    {
      "class": "obj",
      "height": 52.75600348388707,
      "id": "flashlight_0",
      "type": "rect",
      "width": 50.76521089958942,
      "x": 354.36108000497734,
      "y": 327.4853801169594
    },
    {
      "class": "obj",
      "height": 18.5250554848881,
      "id": "flashlight_1",
      "type": "rect",
      "width": 61.75018494962711,
      "x": 256.3467137368302,
      "y": 245.3318158809508
    },
    {
      "class": "obj",
      "height": 85.6140350877194,
      "id": "kleenex_0",
      "type": "rect",
      "width": 73.45029239766092,
      "x": 0,
      "y": 241.8713450292401
    }
  ],
  "class": "image",
  "filename": "wp_3_1_1_001.png"
}
