{
  "annotations": [
    {
      "class": "obj",
      "height": 146.3505098081709,
      "id": "keyboard_0",
      "type": "rect",
      "width": 174.38709165235238,
      "x": 158.0048214619245,
      "y": 308.5787755610279
    },
    {
      "class": "obj",
      "height": 28.489845820960113,
      "id": "onion_1",
      "type": "rect",
      "width": 32.017592210049315,
      "x": 354.2845663185894,
      "y": 285.1430867362821
    },
    {
      "class": "obj",
      "height": 48.091838004473345,
      "id": "stapler_0",
      "type": "rect",
      "width": 71.71172784774365,
      "x": 391,
      "y": 330.6354679802956
    },
    {
      "class": "obj",
      "height": 72.07080115716269,
      "id": "calculator_2",
      "type": "rect",
      "width": 57.93427133193478,
      "x": 329,
      "y": 408
    },
    {
      "class": "obj",
      "height": 62.034304997593836,
      "id": "flashlight_2",
      "type": "rect",
      "width": 26.07709164486488,
      "x": 493.66220971147084,
      "y": 417.70232230823365
    },
    {
      "class": "obj",
      "height": 34.523002923085414,
      "id": "lime_0",
      "type": "rect",
      "width": 36.09155866141242,
      "x": 523.6755805770584,
      "y": 378.688951442646
    },
    {
      "class": "obj",
      "height": 29.87609927758723,
      "id": "banana_2",
      "type": "rect",
      "width": 60.17452232504246,
      "x": 493,
      "y": 338.6488388458832
    },
    {
      "class": "obj",
      "height": 30.98442052172595,
      "id": "lightbulb_0",
      "type": "rect",
      "width": 33.753475631405536,
      "x": 438,
      "y": 280
    },
    {
      "class": "obj",
      "height": 72.24468281986606,
      "id": "soda_can_1",
      "type": "rect",
      "width": 39.76448231850402,
      "x": 161,
      "y": 251
    },
    {
      "class": "obj",
      "height": 39.746625123649096,
      "id": "lemon_0",
      "type": "rect",
      "width": 37.33526328875904,
      "x": 137.3480533423896,
      "y": 327.4122660871045
    },
    {
      "class": "obj",
      "height": 48.68189478822967,
      "id": "glue_stick_1",
      "type": "rect",
      "width": 16.735125500575393,
      "x": 259.86012757166753,
      "y": 254.42926020884636
    },
    {
      "class": "obj",
      "height": 48.64442174602971,
      "id": "calculator_0",
      "type": "rect",
      "width": 55.99187052925603,
      "x": 51.41801548205487,
      "y": 329.95988740323713
    },
    {
      "class": "obj",
      "height": 24.23494199302729,
      "id": "lightbulb_2",
      "type": "rect",
      "width": 61.15735387080031,
      "x": 59.10696692470091,
      "y": 404
    },
    {
      "class": "obj",
      "height": 42.93967919443537,
      "id": "garlic_2",
      "type": "rect",
      "width": 33.882654859585074,
      "x": 217.6755805770584,
      "y": 436.70232230823365
    }
  ],
  "class": "image",
  "filename": "wp_10_1_5_006.png"
}
