{
  "annotations": [
    {
      "class": "obj",
      "height": 172.33787883405472,
      "id": "cereal_box_0",
      "type": "rect",
      "width": 143.21020290392661,
      "x": 236,
      "y": 246
    },
    {
      "class": "obj",
      "height": 74.01323163509193,
      "id": "toothbrush_0",
      "type": "rect",
      "width": 33.072861918620845,
      "x": 416.12865497076024,
      "y": 346.46783625730995
    },
    {
      "class": "obj",
      "height": 110.397407965464,
      "id": "kleenex_0",
      "type": "rect",
      "width": 134.7116547453383,
      "x": 457,
      "y": 262
    },
    {
      "class": "obj",
      "height": 112.13384362499063,
      "id": "toothpaste_0",
      "type": "rect",
      "width": 35.38543094160167,
      "x": 381.33918128654966,
      "y": 106.46783625730995
    },
    {
      "class": "obj",
      "height": 53.31646567671484,
      "id": "coffee_mug_2",
      "type": "rect",
      "width": 52.27352908695485,
      "x": 296.64722790662927,
      "y": 160.2353182723756
    },
    {
      "class": "obj",
      "height": 46.34050557966242,
      "id": "comb_1",
      "type": "rect",
      "width": 30.933626349710636,
      "x": 341.47063654475113,
      "y": 187.29404518287322
    },
    {
      "class": "obj",
      "height": 96.8709342368524,
      "id": "bowl_0",
      "type": "rect",
      "width": 150.05828419665283,
      "x": 71.14619883040938,
      "y": 158.0643274853801
    }
  ],
  "class": "image",
  "filename": "wp_4_4_42_008.png"
}
