{
  "annotations": [
    {
      "class": "obj",
      "height": 122.46191425081406,
      "id": "binder_0",
      "type": "rect",
      "width": 179.14444978927912,
      "x": 317,
      "y": 287
    },
    {
      "class": "obj",
      "height": 27.49576555098463,
      "id": "rubber_eraser_0",
      "type": "rect",
      "width": 32.50254006211574,
      "x": 256,
      "y": 386
    },
    {
      "class": "obj",
      "height": 43.09170677240337,
      "id": "ball_1",
      "type": "rect",
      "width": 42.807145548992914,
      "x": 214.05872691049757,
      "y": 305.7059548171268
    },
    {
      "class": "obj",
      "height": 161.39177719667285,
      "id": "cereal_box_0",
      "type": "rect",
      "width": 102.91086424111577,
      "x": 170.953216374269,
      "y": 149
    },
    {
      "class": "obj",
      "height": 64.62093410168904,
      "id": "cell_phone_0",
      "type": "rect",
      "width": 102.50060727990632,
      "x": 111,
      "y": 398
    },
    {
      "class": "obj",
      "height": 30.432015088602384,
      "id": "stapler_2",
      "type": "rect",
      "width": 32.88438898478529,
      "x": 409,
      "y": 267
    },
    {
      "class": "obj",
      "height": 57.076023391812896,
      "id": "keyboard_1",
      "type": "rect",
      "width": 173.5672514619883,
      "x": 0.6725146198830387,
      "y": 311.6608187134503
    },
    {
      "class": "obj",
      "height": 46.97203702175216,
      "id": "pliers_0",
      "type": "rect",
      "width": 48.102504766300655,
      "x": 33.07367463207058,
      "y": 375.8382748996557
    }
  ],
  "class": "image",
  "filename": "wp_2_1_44_009.png"
}
