{
  "annotations": [
    {
      "class": "obj",
      "height": 164.4075626533996,
      "id": "pitcher_2",
      "type": "rect",
      "width": 109.8279075953067,
      "x": 387.8823001337925,
      "y": 61
    },
    {
      "class": "obj",
      "height": 36.620306042028176,
      "id": "peach_0",
      "type": "rect",
      "width": 44.065929169865456,
      "x": 484.5588499331037,
      "y": 347
    },
    {
      "class": "obj",
      "height": 56.76323429863237,
      "id": "pear_0",
      "type": "rect",
      "width": 45.740368066995586,
      "x": 437,
      "y": 344
    },
    {
      "class": "obj",
      "height": 78.76769219234905,
      "id": "food_jar_0",
      "type": "rect",
      "width": 44.764950375220565,
      "x": 540.6765497993111,
      "y": 281.72057503344814
    },
    {
      "class": "obj",
      "height": 51.71986846558843,
      "id": "coffee_mug_2",
      "type": "rect",
      "width": 55.174138821466215,
      "x": 584.3090743644855,
      "y": 285.35309959862246
    },
    {
      "class": "obj",
      "height": 103.81221492889489,
      "id": "food_bag_2",
      "type": "rect",
      "width": 105.7835701979638,
      "x": 315.0440252341369,
      "y": 338
    },
    {
      "class": "obj",
      "height": 80.48698807482137,
      "id": "bell_pepper_1",
      "type": "rect",
      "width": 81.1496195620598,
      "x": 203.07367463207058,
      "y": 152.99999999999997
    },
    {
      "class": "obj",
      "height": 46.23754367623124,
      "id": "mushroom_1",
      "type": "rect",
      "width": 49.42138380160712,
      "x": 171.07367463207058,
      "y": 213
    },
    {
      "class": "obj",
      "height": 139.34972675925067,
      "id": "soda_can_2",
      "type": "rect",
      "width": 82.36471704323158,
      "x": 85.98562416379677,
      "y": 127.27942496655186
    }
  ],
  "class": "image",
  "filename": "wp_3_4_66_009.png"
}
