{
  "annotations": [
    {
      "class": "obj",
      "height": 45.88924272958468,
      "id": "stapler_2",
      "type": "rect",
      "width": 73.70111767500673,
      "x": 170.23539973241495,
      "y": 301.39712483275935
    },
    {
      "class": "obj",
      "height": 105.4104622636086,
      "id": "cereal_box_0",
      "type": "rect",
      "width": 101.28320252267021,
      "x": 55.47079946482994,
      "y": 224.79424966551875
    },
    {
      "class": "obj",
      "height": 251.69590643274847,
      "id": "binder_0",
      "type": "rect",
      "width": 102.92397660818712,
      "x": 0.20467836257310523,
      "y": 211.5789473684211
    }
  ],
  "class": "image",
  "filename": "wp_2_2_64_004.png"
}
