{
  "annotations": [
    {
      "class": "obj",
      "height": 21.683301034462346,
      "id": "lemon_2",
      "type": "rect",
      "width": 18.372256229637287,
      "x": 621.7426900584795,
      "y": 188
    },
    {
      "class": "obj",
      "height": 35.57446868177328,
      "id": "food_bag_1",
      "type": "rect",
      "width": 44.77578905230112,
      "x": 595.1461988304093,
      "y": 228
    },
    {
      "class": "obj",
      "height": 123.04093567251459,
      "id": "hand_towel_1",
      "type": "rect",
      "width": 162.80701754385967,
      "x": 476.87134502923976,
      "y": 328.46783625730995
    }
  ],
  "class": "image",
  "filename": "wp_7_3_78_016.png"
}
