{
  "annotations": [
    {
      "class": "obj",
      "height": 36.4990282236642,
      "id": "peach_2",
      "type": "rect",
      "width": 36.145565436715515,
      "x": 455.78797840567637,
      "y": 287.7879784056762
    },
    {
      "class": "obj",
      "height": 62.44433913279468,
      "id": "banana_1",
      "type": "rect",
      "width": 61.772797526847995,
      "x": 308,
      "y": 171
    },
    {
      "class": "obj",
      "height": 54.697930305410864,
      "id": "food_can_1",
      "type": "rect",
      "width": 56.49726272237751,
      "x": 384.60601079716184,
      "y": 318.42404318864743
    },
    {
      "class": "obj",
      "height": 108.58805946928288,
      "id": "shampoo_2",
      "type": "rect",
      "width": 44.383813893269576,
      "x": 319,
      "y": 301
    },
    {
      "class": "obj",
      "height": 34.14296331178522,
      "id": "tomato_2",
      "type": "rect",
      "width": 33.86228242091164,
      "x": 288.9907925842976,
      "y": 181.3364024719008
    },
    {
      "class": "obj",
      "height": 87.97560536772684,
      "id": "toothpaste_2",
      "type": "rect",
      "width": 36.97837938094894,
      "x": 248.64978640454564,
      "y": 127.00000000000003
    },
    {
      "class": "obj",
      "height": 139.38947099378402,
      "id": "water_bottle_1",
      "type": "rect",
      "width": 58.03918188633391,
      "x": 206.46783625730995,
      "y": 290.46783625730995
    },
    {
      "class": "obj",
      "height": 83.83559371241341,
      "id": "food_cup_0",
      "type": "rect",
      "width": 99.60598896769109,
      "x": 43.96317033719049,
      "y": 186.65899382024799
    }
  ],
  "class": "image",
  "filename": "wp_5_4_48_006.png"
}
