{
  "annotations": [
    {
      "class": "obj",
      "height": 91.29524188522484,
      "id": "soda_can_1",
      "type": "rect",
      "width": 38.25445772671466,
      "x": 303.2489045697583,
      "y": 124
    },
    {
      "class": "obj",
      "height": 37.20314434887945,
      "id": "sponge_2",
      "type": "rect",
      "width": 47.11322082114225,
      "x": 468.4203607808999,
      "y": 298.76327320318336
    },
    {
      "class": "obj",
      "height": 33.214931413091904,
      "id": "banana_2",
      "type": "rect",
      "width": 33.88704143988127,
      "x": 426.6692653506583,
      "y": 322.8285437888584
    },
    {
      "class": "obj",
      "height": 76.66393319608125,
      "id": "bowl_1",
      "type": "rect",
      "width": 90.38480094214668,
      "x": 342.86945882865,
      "y": 319.1714562111417
    },
    {
      "class": "obj",
      "height": 58.24209863973795,
      "id": "tomato_0",
      "type": "rect",
      "width": 71.02097208858001,
      "x": 208.4203607809,
      "y": 371.59181699204163
    },
    {
      "class": "obj",
      "height": 33.74272615571576,
      "id": "onion_1",
      "type": "rect",
      "width": 39.57137693330651,
      "x": 261.01217777294164,
      "y": 179.11836339840838
    },
    {
      "class": "obj",
      "height": 32.52992036204034,
      "id": "garlic_2",
      "type": "rect",
      "width": 42.5976613825417,
      "x": 290,
      "y": 395
    },
    {
      "class": "obj",
      "height": 22.478705401784197,
      "id": "onion_0",
      "type": "rect",
      "width": 24.17521146984342,
      "x": 359.18363398408343,
      "y": 182.644909804775
    },
    {
      "class": "obj",
      "height": 63.38980731292031,
      "id": "lemon_1",
      "type": "rect",
      "width": 73.40007315975886,
      "x": 69.41232026463894,
      "y": 209.52895282486352
    },
    {
      "class": "obj",
      "height": 52.2406564673845,
      "id": "lime_0",
      "type": "rect",
      "width": 54.35852091876492,
      "x": 1.8825461790048457,
      "y": 244.49568499825432
    }
  ],
  "class": "image",
  "filename": "wp_9_4_90_004.png"
}
