{
  "annotations": [
    {
      "class": "obj",
      "height": 82.24812509306554,
      "id": "soda_can_0",
      "type": "rect",
      "width": 49.72158869969462,
      "x": 564.9999999999999,
      "y": 334
    },
    {
      "class": "obj",
      "height": 65.07045946210178,
      "id": "food_can_2",
      "type": "rect",
      "width": 52.48268391073913,
      "x": 562.7426900584796,
      "y": 293
    },
    {
      "class": "obj",
      "height": 74.53349847948996,
      "id": "cap_2",
      "type": "rect",
      "width": 97.12402086241491,
      "x": 542.5204678362571,
      "y": 261.7894736842106
    },
    {
      "class": "obj",
      "height": 48.265034540656245,
      "id": "plate_0",
      "type": "rect",
      "width": 96.07844782116692,
      "x": 436,
      "y": 296
    },
    {
      "class": "obj",
      "height": 76.7728801329389,
      "id": "bowl_2",
      "type": "rect",
      "width": 98.55309460302584,
      "x": 361.1929824561403,
      "y": 301.53216374269005
    },
    {
      "class": "obj",
      "height": 72.22768391648043,
      "id": "kleenex_2",
      "type": "rect",
      "width": 67.41737358370088,
      "x": 492,
      "y": 198
    },
    {
      "class": "obj",
      "height": 69.22055320450815,
      "id": "binder_2",
      "type": "rect",
      "width": 114.51819050089344,
      "x": 431.8829568093902,
      "y": 182.0587269104976
    },
    {
      "class": "obj",
      "height": 40.10607580062995,
      "id": "pitcher_1",
      "type": "rect",
      "width": 52.73219244389702,
      "x": 465.8238192685073,
      "y": 151.35277209337076
    },
    {
      "class": "obj",
      "height": 35.8803163136252,
      "id": "food_jar_1",
      "type": "rect",
      "width": 24.97116464370839,
      "x": 540.6945062890278,
      "y": 185.60843451283674
    }
  ],
  "class": "image",
  "filename": "wp_8_3_45_011.png"
}
