{
  "annotations": [
    {
      "class": "obj",
      "height": 53.20334695058028,
      "id": "scissors_0",
      "type": "rect",
      "width": 58.60590425364012,
      "x": 404.5041693143023,
      "y": 313.94212815872095
    },
    {
      "class": "obj",
      "height": 111.42589629556608,
      "id": "keyboard_1",
      "type": "rect",
      "width": 299.3952753540348,
      "x": 290,
      "y": 368.1663216588268
    },
    {
      "class": "obj",
      "height": 72.9716474772996,
      "id": "plate_1",
      "type": "rect",
      "width": 114.55503972326225,
      "x": 209.27789278039106,
      "y": 342
    },
    {
      "class": "obj",
      "height": 39.65432210234462,
      "id": "apple_2",
      "type": "rect",
      "width": 32.89346326989235,
      "x": 312.1942128158721,
      "y": 285.97106407936053
    },
    {
      "class": "obj",
      "height": 105.92842214882205,
      "id": "food_box_1",
      "type": "rect",
      "width": 88.63555690988947,
      "x": 198.35537155137433,
      "y": 200
    },
    {
      "class": "obj",
      "height": 27.83088333805847,
      "id": "cell_phone_0",
      "type": "rect",
      "width": 75.99111548435266,
      "x": 165,
      "y": 316
    },
    {
      "class": "obj",
      "height": 24.313688063631105,
      "id": "marker_2",
      "type": "rect",
      "width": 64.4071531365156,
      "x": 347,
      "y": 267.8347231047674
    },
    {
      "class": "obj",
      "height": 116.227387729886,
      "id": "shampoo_1",
      "type": "rect",
      "width": 55.08517049216566,
      "x": 83.07747877098328,
      "y": 336.08884288784355
    },
    {
      "class": "obj",
      "height": 177.50939332480738,
      "id": "cereal_box_0",
      "type": "rect",
      "width": 128.63668030394825,
      "x": 0.4829669233856997,
      "y": 164.08884288784358
    },
    {
      "class": "obj",
      "height": 50.56586371145585,
      "id": "pliers_2",
      "type": "rect",
      "width": 54.964788978343925,
      "x": 15.1115711215642,
      "y": 342.63326433176536
    }
  ],
  "class": "image",
  "filename": "wp_2_1_4_007.png"
}
