{
  "annotations": [
    {
      "class": "obj",
      "height": 22.724698781652705,
      "id": "calculator_0",
      "type": "rect",
      "width": 61.595894066058804,
      "x": 351.036794337636,
      "y": 275.4871378617905
    },
    {
      "class": "obj",
      "height": 31.296295690521788,
      "id": "stapler_0",
      "type": "rect",
      "width": 49.43618682324461,
      "x": 339.4751054838127,
      "y": 234.82188741041182
    },
    {
      "class": "obj",
      "height": 31.760756639304702,
      "id": "potato_1",
      "type": "rect",
      "width": 38.78747270994728,
      "x": 241.43796418728078,
      "y": 247.6214743294463
    },
    {
      "class": "obj",
      "height": 37.94426678147022,
      "id": "lightbulb_0",
      "type": "rect",
      "width": 56.49479720796677,
      "x": 280.22543689722806,
      "y": 337.0013027480205
    },
    {
      "class": "obj",
      "height": 87.97448520444573,
      "id": "hand_towel_2",
      "type": "rect",
      "width": 155.9930967682664,
      "x": 384.50190338556473,
      "y": 292.5924571815591
    },
    {
      "class": "obj",
      "height": 47.556814366109336,
      "id": "lemon_0",
      "type": "rect",
      "width": 42.80113292949841,
      "x": 179.92328101844694,
      "y": 373.3209927739582
    },
    {
      "class": "obj",
      "height": 32.893463269892266,
      "id": "camera_2",
      "type": "rect",
      "width": 48.745734725262054,
      "x": 176.35651994098876,
      "y": 306.74145266140516
    },
    {
      "class": "obj",
      "height": 33.68607684266078,
      "id": "ball_2",
      "type": "rect",
      "width": 32.100849697123806,
      "x": 272.26276224597586,
      "y": 277.8110572553553
    },
    {
      "class": "obj",
      "height": 109.77697982843569,
      "id": "cereal_box_2",
      "type": "rect",
      "width": 75.29828941300643,
      "x": 127.6107852157267,
      "y": 188.24572353251608
    },
    {
      "class": "obj",
      "height": 33.72823713908463,
      "id": "onion_2",
      "type": "rect",
      "width": 37.6631981386445,
      "x": 86.28807334749152,
      "y": 304.9594774658902
    },
    {
      "class": "obj",
      "height": 43.00350235233293,
      "id": "lightbulb_2",
      "type": "rect",
      "width": 26.42045242561629,
      "x": 116.362418129842,
      "y": 367.63778481602253
    },
    {
      "class": "obj",
      "height": 49.732538623358835,
      "id": "bell_pepper_0",
      "type": "rect",
      "width": 46.37978321054813,
      "x": 9.49947366963034,
      "y": 298.95402430895484
    },
    {
      "class": "obj",
      "height": 76.5545819258445,
      "id": "pliers_1",
      "type": "rect",
      "width": 32.9687615593053,
      "x": 1.6763777064053542,
      "y": 376.6261913724029
    }
  ],
  "class": "image",
  "filename": "wp_9_1_1_001.png"
}
