{
  "annotations": [
    {
      "class": "obj",
      "height": 118.22660098522164,
      "id": "hand_towel_0",
      "type": "rect",
      "width": 170.2463054187192,
      "x": 193.89162561576353,
      "y": 322.5221674876847
    },
    {
      "class": "obj",
      "height": 101.20197044334975,
      "id": "cap_0",
      "type": "rect",
      "width": 160.78817733990147,
      "x": 17.02463054187192,
      "y": 320.63054187192114
    },
    {
      "class": "obj",
      "height": 24.500457525230843,
      "id": "toothbrush_0",
      "type": "rect",
      "width": 83.72971892117707,
      "x": 149.61929886767152,
      "y": 320.64676450496216
    },
    {
      "class": "obj",
      "height": 32.58798719375358,
      "id": "camera_0",
      "type": "rect",
      "width": 41.86485946058852,
      "x": 213.13019361754164,
      "y": 280.68485320167315
    },
    {
      "class": "obj",
      "height": 55.89910212067218,
      "id": "bowl_0",
      "type": "rect",
      "width": 77.78300592961621,
      "x": 113.9390209183063,
      "y": 255.2329215977926
    },
    {
      "class": "obj",
      "height": 79.4480855672532,
      "id": "kleenex_0",
      "type": "rect",
      "width": 51.14173172742352,
      "x": 167.2215693226917,
      "y": 203.61545283104425
    },
    {
      "class": "obj",
      "height": 52.806811365060554,
      "id": "greens_1",
      "type": "rect",
      "width": 96.57461898294858,
      "x": 245.48031229163277,
      "y": 163.41567300809274
    },
    {
      "class": "obj",
      "height": 18.553744533669914,
      "id": "flashlight_0",
      "type": "rect",
      "width": 25.21406308421814,
      "x": 322.54971266226164,
      "y": 170.07599155864094
    },
    {
      "class": "obj",
      "height": 25.927668643205408,
      "id": "calculator_1",
      "type": "rect",
      "width": 63.03515771054521,
      "x": 326.35560897686065,
      "y": 236.2034400247978
    },
    {
      "class": "obj",
      "height": 24.7383260448932,
      "id": "scissors_2",
      "type": "rect",
      "width": 67.31679106446904,
      "x": 289.01025138985835,
      "y": 260.7038975500286
    },
    {
      "class": "obj",
      "height": 49.23878357012401,
      "id": "notebook_2",
      "type": "rect",
      "width": 108.94378200539515,
      "x": 215.27101029450355,
      "y": 211.4651139799046
    },
    {
      "class": "obj",
      "height": 27.11701124151756,
      "id": "marker_1",
      "type": "rect",
      "width": 27.830616800504856,
      "x": 258.32521235340425,
      "y": 248.334734527582
    },
    {
      "class": "obj",
      "height": 72.31202997738023,
      "id": "notebook_1",
      "type": "rect",
      "width": 150.33290442665884,
      "x": 282.82566987863504,
      "y": 272.8351920528128
    },
    {
      "class": "obj",
      "height": 36.25817897388933,
      "id": "keyboard_2",
      "type": "rect",
      "width": 48.47778625238237,
      "x": 187.70118065488558,
      "y": 191.70760927078493
    },
    {
      "class": "obj",
      "height": 26.442428864935863,
      "id": "notebook_0",
      "type": "rect",
      "width": 55.88967919179623,
      "x": 190.70600211681008,
      "y": 162.06003751312957
    },
    {
      "class": "obj",
      "height": 93.20956174889889,
      "id": "cereal_box_0",
      "type": "rect",
      "width": 65.24669322422922,
      "x": 123.99696244777762,
      "y": 139.53188940592744
    }
  ],
  "class": "image",
  "filename": "wp_3_3_7_001.png"
}
