{
  "annotations": [
    {
      "class": "obj",
      "height": 71.06328722118229,
      "id": "stapler_2",
      "type": "rect",
      "width": 33.95482473574339,
      "x": 495,
      "y": 338
    },
    {
      "class": "obj",
      "height": 32.180333308825425,
      "id": "potato_0",
      "type": "rect",
      "width": 48.438051755584176,
      "x": 460,
      "y": 287
    },
    {
      "class": "obj",
      "height": 50.29522494042203,
      "id": "marker_2",
      "type": "rect",
      "width": 48.07502401594138,
      "x": 574.5459028255432,
      "y": 330
    },
    {
      "class": "obj",
      "height": 93.75633915239149,
      "id": "keyboard_1",
      "type": "rect",
      "width": 267.41142135787436,
      "x": 202.80701754385964,
      "y": 338.48538011695905
    },
    {
      "class": "obj",
      "height": 24.094486664651015,
      "id": "pliers_2",
      "type": "rect",
      "width": 121.72896773905026,
      "x": 429.1298245614035,
      "y": 455.95789473684215
    },
    {
      "class": "obj",
      "height": 87.16732555416354,
      "id": "food_box_1",
      "type": "rect",
      "width": 107.29983517786857,
      "x": 313,
      "y": 246
    },
    {
      "class": "obj",
      "height": 33.835695344091334,
      "id": "cell_phone_0",
      "type": "rect",
      "width": 75.77253065252565,
      "x": 209,
      "y": 301
    },
    {
      "class": "obj",
      "height": 13.998726525595771,
      "id": "rubber_eraser_2",
      "type": "rect",
      "width": 23.727111542936363,
      "x": 203,
      "y": 264
    },
    {
      "class": "obj",
      "height": 31.63163106104753,
      "id": "garlic_0",
      "type": "rect",
      "width": 38.44424434980125,
      "x": 151.29445581325848,
      "y": 320.52936345524876
    },
    {
      "class": "obj",
      "height": 17.483875458752635,
      "id": "marker_0",
      "type": "rect",
      "width": 46.0058488607292,
      "x": 169.35318272375605,
      "y": 250.0587269104976
    },
    {
      "class": "obj",
      "height": 23.919923565440115,
      "id": "scissors_0",
      "type": "rect",
      "width": 40.41328370835264,
      "x": 170.64722790662924,
      "y": 224.7059548171268
    },
    {
      "class": "obj",
      "height": 23.675292121095595,
      "id": "comb_2",
      "type": "rect",
      "width": 84.17973756578314,
      "x": 93.52977408563409,
      "y": 376.58850099613164
    },
    {
      "class": "obj",
      "height": 55.88918481512735,
      "id": "coffee_mug_1",
      "type": "rect",
      "width": 54.43490617548475,
      "x": 102,
      "y": 263
    },
    {
      "class": "obj",
      "height": 47.71929824561403,
      "id": "coffee_mug_0",
      "type": "rect",
      "width": 39.76608187134502,
      "x": 66,
      "y": 219
    },
    {
      "class": "obj",
      "height": 46.11696039744896,
      "id": "ball_1",
      "type": "rect",
      "width": 45.548926237733504,
      "x": 46.58734889730561,
      "y": 316.8649610900693
    },
    {
      "class": "obj",
      "height": 182.72280701754386,
      "id": "cereal_box_0",
      "type": "rect",
      "width": 44.8561403508772,
      "x": 0,
      "y": 163.59298245614036
    }
  ],
  "class": "image",
  "filename": "wp_1_1_26_019.png"
}
