{
  "annotations": [
    {
      "class": "obj",
      "height": 123.01231578586174,
      "id": "greens_0",
      "type": "rect",
      "width": 131.78470498635525,
      "x": 507.88688866809593,
      "y": 272.8180323914856
    },
    {
      "class": "obj",
      "height": 74.95689383582692,
      "id": "coffee_mug_0",
      "type": "rect",
      "width": 68.04035382612183,
      "x": 399.8271337282704,
      "y": 151.8756100133721
    },
    {
      "class": "obj",
      "height": 73.11564260843,
      "id": "sponge_1",
      "type": "rect",
      "width": 69.3301727566965,
      "x": 297.57595681135257,
      "y": 364.19817373514314
    },
    {
      "class": "obj",
      "height": 45.523176049988706,
      "id": "lime_1",
      "type": "rect",
      "width": 44.398554391460124,
      "x": 391,
      "y": 430
    },
    {
      "class": "obj",
      "height": 68.81326889303296,
      "id": "coffee_mug_1",
      "type": "rect",
      "width": 53.07219524038864,
      "x": 320.54603623161336,
      "y": 151.85945125167152
    },
    {
      "class": "obj",
      "height": 105.75679628376207,
      "id": "food_jar_2",
      "type": "rect",
      "width": 101.62556437884558,
      "x": 77.10332403000425,
      "y": 174
    },
    {
      "class": "obj",
      "height": 57.21905192818272,
      "id": "lime_2",
      "type": "rect",
      "width": 42.77540775213659,
      "x": 1.1110495520035477,
      "y": 237.7646041287592
    },
    {
      "class": "obj",
      "height": 19.789473684210577,
      "id": "food_can_0",
      "type": "rect",
      "width": 60.02807017543864,
      "x": 288.266666666667,
      "y": 460.43508771929874
    }
  ],
  "class": "image",
  "filename": "wp_2_4_66_014.png"
}
