{
  "annotations": [
    {
      "class": "obj",
      "height": 56.005748825394164,
      "id": "stapler_1",
      "type": "rect",
      "width": 45.88706311324313,
      "x": 415,
      "y": 336
    },
    {
      "class": "obj",
      "height": 54.358520918764896,
      "id": "pear_1",
      "type": "rect",
      "width": 61.18275081765745,
      "x": 289.1819676085144,
      "y": 359.99999999999994
    },
    {
      "class": "obj",
      "height": 57.18234018727219,
      "id": "food_cup_1",
      "type": "rect",
      "width": 36.87067968850516,
      "x": 372.60365252971366,
      "y": 273
    },
    {
      "class": "obj",
      "height": 24.771716892896336,
      "id": "toothpaste_1",
      "type": "rect",
      "width": 64.60463765667362,
      "x": 368,
      "y": 266
    },
    {
      "class": "obj",
      "height": 16.052072546596804,
      "id": "glue_stick_0",
      "type": "rect",
      "width": 32.69866629862315,
      "x": 367,
      "y": 239
    },
    {
      "class": "obj",
      "height": 30.122407741761947,
      "id": "lightbulb_1",
      "type": "rect",
      "width": 54.29960342922874,
      "x": 315,
      "y": 276
    },
    {
      "class": "obj",
      "height": 81.89075878671076,
      "id": "water_bottle_2",
      "type": "rect",
      "width": 36.00369567346766,
      "x": 257,
      "y": 261
    },
    {
      "class": "obj",
      "height": 107.55905237481159,
      "id": "greens_2",
      "type": "rect",
      "width": 122.13665287982269,
      "x": 112.75792441986695,
      "y": 235.36393521702882
    },
    {
      "class": "obj",
      "height": 102.72677463828535,
      "id": "food_bag_0",
      "type": "rect",
      "width": 106.32177058782128,
      "x": 102.3639352170288,
      "y": 334.1819676085144
    },
    {
      "class": "obj",
      "height": 34.15334584382305,
      "id": "food_box_0",
      "type": "rect",
      "width": 86.1563827253643,
      "x": 187,
      "y": 215
    },
    {
      "class": "obj",
      "height": 30.49907838728231,
      "id": "bell_pepper_2",
      "type": "rect",
      "width": 29.09359090399741,
      "x": 239.43806145689067,
      "y": 179.93232370129257
    },
    {
      "class": "obj",
      "height": 41.82969982167907,
      "id": "cap_1",
      "type": "rect",
      "width": 72.32877820896137,
      "x": 154.4919990838385,
      "y": 182.4951994503031
    },
    {
      "class": "obj",
      "height": 20.88295232256641,
      "id": "shampoo_0",
      "type": "rect",
      "width": 30.461200001208,
      "x": 236,
      "y": 168
    },
    {
      "class": "obj",
      "height": 17.97728139081073,
      "id": "mushroom_0",
      "type": "rect",
      "width": 29.02979572745116,
      "x": 276.0964795968889,
      "y": 164.0996799633535
    },
    {
      "class": "obj",
      "height": 14.435652292859487,
      "id": "dry_battery_0",
      "type": "rect",
      "width": 6.963642239878254,
      "x": 326.4983998167677,
      "y": 169.69775974347476
    },
    {
      "class": "obj",
      "height": 13.492679839535015,
      "id": "dry_battery_2",
      "type": "rect",
      "width": 5.9030474297965725,
      "x": 336.8683163720003,
      "y": 181.86831637200038
    },
    {
      "class": "obj",
      "height": 14.335972329505978,
      "id": "cell_phone_2",
      "type": "rect",
      "width": 42.16462449854697,
      "x": 281,
      "y": 186
    },
    {
      "class": "obj",
      "height": 16.55025960177133,
      "id": "cell_phone_1",
      "type": "rect",
      "width": 41.45197086682879,
      "x": 337.09967996335354,
      "y": 212.10288032981816
    },
    {
      "class": "obj",
      "height": 36.71632618626472,
      "id": "instant_noodles_2",
      "type": "rect",
      "width": 64.92114039298627,
      "x": 277,
      "y": 203
    },
    {
      "class": "obj",
      "height": 67.92520344458978,
      "id": "kleenex_1",
      "type": "rect",
      "width": 82.27794913558418,
      "x": 253,
      "y": 224
    }
  ],
  "class": "image",
  "filename": "wp_5_3_89_002.png"
}
