{
  "annotations": [
    {
      "class": "obj",
      "height": 55.770430553018514,
      "id": "stapler_1",
      "type": "rect",
      "width": 54.38759510114022,
      "x": 513,
      "y": 355
    },
    {
      "class": "obj",
      "height": 51.82891141830373,
      "id": "pear_1",
      "type": "rect",
      "width": 65.60944358831114,
      "x": 381,
      "y": 366.4119096342536
    },
    {
      "class": "obj",
      "height": 57.88829500439897,
      "id": "food_cup_1",
      "type": "rect",
      "width": 42.28299995314404,
      "x": 473.823408638122,
      "y": 284
    },
    {
      "class": "obj",
      "height": 34.29639511633434,
      "id": "toothpaste_1",
      "type": "rect",
      "width": 72.51043083596284,
      "x": 470.88254617900486,
      "y": 270.823408638122
    },
    {
      "class": "obj",
      "height": 19.480654957215023,
      "id": "glue_stick_0",
      "type": "rect",
      "width": 36.68944370255531,
      "x": 470.8238192685073,
      "y": 245.05872691049757
    },
    {
      "class": "obj",
      "height": 31.29899910363997,
      "id": "lightbulb_1",
      "type": "rect",
      "width": 54.44336325304164,
      "x": 415,
      "y": 282
    },
    {
      "class": "obj",
      "height": 80.09642599605849,
      "id": "water_bottle_2",
      "type": "rect",
      "width": 36.18012245017272,
      "x": 355,
      "y": 262
    },
    {
      "class": "obj",
      "height": 103.05868330699306,
      "id": "greens_2",
      "type": "rect",
      "width": 118.40113012480154,
      "x": 218,
      "y": 228
    },
    {
      "class": "obj",
      "height": 94.4615609227638,
      "id": "food_bag_0",
      "type": "rect",
      "width": 100.32152620770316,
      "x": 201,
      "y": 324
    },
    {
      "class": "obj",
      "height": 31.839803106139613,
      "id": "food_box_0",
      "type": "rect",
      "width": 82.08249923262926,
      "x": 294,
      "y": 214
    },
    {
      "class": "obj",
      "height": 29.625232224895456,
      "id": "bell_pepper_2",
      "type": "rect",
      "width": 27.88531399614814,
      "x": 344.65215547125274,
      "y": 178.99917873922942
    },
    {
      "class": "obj",
      "height": 39.85757387228,
      "id": "cap_1",
      "type": "rect",
      "width": 68.19865111556423,
      "x": 262.88254617900486,
      "y": 178.9412730895024
    },
    {
      "class": "obj",
      "height": 20.771664053004827,
      "id": "shampoo_0",
      "type": "rect",
      "width": 32.227894890109155,
      "x": 340.2649387349564,
      "y": 166.57835375501455
    },
    {
      "class": "obj",
      "height": 18.423661227708266,
      "id": "mushroom_0",
      "type": "rect",
      "width": 29.62174190299251,
      "x": 382.26493873495644,
      "y": 164.5783537550145
    },
    {
      "class": "obj",
      "height": 14.435652292859487,
      "id": "dry_battery_0",
      "type": "rect",
      "width": 6.963642239878254,
      "x": 434.34876942500046,
      "y": 172.23262121155528
    },
    {
      "class": "obj",
      "height": 13.492679839535015,
      "id": "dry_battery_2",
      "type": "rect",
      "width": 5.9030474297965725,
      "x": 443.9789611313227,
      "y": 185.80609485959317
    },
    {
      "class": "obj",
      "height": 15.296887176234094,
      "id": "cell_phone_2",
      "type": "rect",
      "width": 43.84124148215358,
      "x": 384.40548748328496,
      "y": 187.14054874832848
    },
    {
      "class": "obj",
      "height": 19.544454034151613,
      "id": "cell_phone_1",
      "type": "rect",
      "width": 44.324053178230486,
      "x": 441.7059548171268,
      "y": 215.2940451828732
    },
    {
      "class": "obj",
      "height": 37.73731196179662,
      "id": "instant_noodles_2",
      "type": "rect",
      "width": 66.13105993016472,
      "x": 379,
      "y": 206
    },
    {
      "class": "obj",
      "height": 65.74529235801495,
      "id": "kleenex_1",
      "type": "rect",
      "width": 83.7270033070703,
      "x": 354,
      "y": 225
    }
  ],
  "class": "image",
  "filename": "wp_5_3_89_006.png"
}
