{
  "annotations": [
    {
      "class": "obj",
      "height": 155.586446229565,
      "id": "cereal_box_0",
      "type": "rect",
      "width": 105.7962979110354,
      "x": 193.3391812865497,
      "y": 149
    },
    {
      "class": "obj",
      "height": 37.142818829482906,
      "id": "garlic_0",
      "type": "rect",
      "width": 42.81464545486997,
      "x": 175,
      "y": 339.94127308950243
    },
    {
      "class": "obj",
      "height": 37.446915195106214,
      "id": "marker_2",
      "type": "rect",
      "width": 69.49862548002935,
      "x": 93.8679242975893,
      "y": 271.72057503344814
    },
    {
      "class": "obj",
      "height": 20.73363247152622,
      "id": "rubber_eraser_2",
      "type": "rect",
      "width": 33.10312347531405,
      "x": 103.83581630931323,
      "y": 387.33243043297705
    },
    {
      "class": "obj",
      "height": 26.06477893555831,
      "id": "marker_0",
      "type": "rect",
      "width": 54.74221770920162,
      "x": 69.51015762900867,
      "y": 319.667569567023
    },
    {
      "class": "obj",
      "height": 103.85326518363655,
      "id": "keyboard_1",
      "type": "rect",
      "width": 170.74272062802444,
      "x": 0.6900279099872506,
      "y": 238.4035087719298
    },
    {
      "class": "obj",
      "height": 39.146208344064235,
      "id": "coffee_mug_0",
      "type": "rect",
      "width": 34.43588579790605,
      "x": 29.353099598622443,
      "y": 200.1176998662075
    },
    {
      "class": "obj",
      "height": 69.44059700022177,
      "id": "food_box_1",
      "type": "rect",
      "width": 57.824454060714,
      "x": 19.41150066896259,
      "y": 132
    },
    {
      "class": "obj",
      "height": 46.10511948105864,
      "id": "comb_2",
      "type": "rect",
      "width": 64.82659224003399,
      "x": 8.662173963107982,
      "y": 340.89845919328206
    },
    {
      "class": "obj",
      "height": 24.553108539670717,
      "id": "tomato_1",
      "type": "rect",
      "width": 22.230517191323464,
      "x": 1.3271950561984158,
      "y": 231.26373854257395
    },
    {
      "class": "obj",
      "height": 7.631371573140882,
      "id": "rubber_eraser_0",
      "type": "rect",
      "width": 14.930944382232177,
      "x": 2.6543901123968316,
      "y": 186.47090539587742
    }
  ],
  "class": "image",
  "filename": "wp_1_2_64_007.png"
}
