{
  "annotations": [
    {
      "class": "obj",
      "height": 46.82629208065916,
      "id": "bell_pepper_2",
      "type": "rect",
      "width": 46.55540058403784,
      "x": 538.9677740450417,
      "y": 271.66820123595033
    },
    {
      "class": "obj",
      "height": 98.04972868534588,
      "id": "water_bottle_2",
      "type": "rect",
      "width": 51.644512851431756,
      "x": 549.7942496655187,
      "y": 320.044025234137
    },
    {
      "class": "obj",
      "height": 82.76806116808567,
      "id": "toothpaste_1",
      "type": "rect",
      "width": 29.875584226819342,
      "x": 584.191374498278,
      "y": 278.1320757024107
    },
    {
      "class": "obj",
      "height": 48.89143595600359,
      "id": "glue_stick_0",
      "type": "rect",
      "width": 18.179026144465013,
      "x": 460,
      "y": 343.19817373514314
    },
    {
      "class": "obj",
      "height": 65.9941599416093,
      "id": "kleenex_1",
      "type": "rect",
      "width": 101.36785077994082,
      "x": 444.6635975280993,
      "y": 221.99079258429762
    },
    {
      "class": "obj",
      "height": 75.04755815245525,
      "id": "food_bag_0",
      "type": "rect",
      "width": 52.89058907343065,
      "x": 386.3364024719008,
      "y": 229
    },
    {
      "class": "obj",
      "height": 49.3523901156409,
      "id": "lightbulb_1",
      "type": "rect",
      "width": 26.116560096038896,
      "x": 380,
      "y": 324
    },
    {
      "class": "obj",
      "height": 82.79560410226708,
      "id": "shampoo_0",
      "type": "rect",
      "width": 37.621229637021486,
      "x": 450,
      "y": 263
    },
    {
      "class": "obj",
      "height": 50.50530807155843,
      "id": "toothbrush_2",
      "type": "rect",
      "width": 30.27247616696399,
      "x": 309.4582190796812,
      "y": 301.57322576930704
    },
    {
      "class": "obj",
      "height": 83.46161679952789,
      "id": "greens_2",
      "type": "rect",
      "width": 113.81014024617645,
      "x": 264,
      "y": 202
    },
    {
      "class": "obj",
      "height": 37.9136136815963,
      "id": "cell_phone_2",
      "type": "rect",
      "width": 56.870268829601585,
      "x": 229.76468172762443,
      "y": 287.2940451828731
    },
    {
      "class": "obj",
      "height": 73.24600522250671,
      "id": "food_box_0",
      "type": "rect",
      "width": 152.19462317164633,
      "x": 136.05913754088286,
      "y": 311.4706365447512
    },
    {
      "class": "obj",
      "height": 27.51914014577784,
      "id": "pear_1",
      "type": "rect",
      "width": 26.85873072820734,
      "x": 211.35318272375608,
      "y": 257.8238192685073
    },
    {
      "class": "obj",
      "height": 88.75743286894706,
      "id": "pitcher_0",
      "type": "rect",
      "width": 72.66447781648303,
      "x": 172.23572890276094,
      "y": 153.47063654475122
    },
    {
      "class": "obj",
      "height": 32.31006224178569,
      "id": "instant_noodles_2",
      "type": "rect",
      "width": 75.85635294546788,
      "x": 129.23572890276094,
      "y": 222.41190963425362
    },
    {
      "class": "obj",
      "height": 26.907631673455228,
      "id": "mushroom_0",
      "type": "rect",
      "width": 42.02948163294872,
      "x": 121.41232026463894,
      "y": 259.9412730895024
    },
    {
      "class": "obj",
      "height": 96.33786526911138,
      "id": "cap_1",
      "type": "rect",
      "width": 100.36627877390941,
      "x": 24.764681727624392,
      "y": 267.88254617900486
    }
  ],
  "class": "image",
  "filename": "wp_5_1_1_013.png"
}
